dodrio/__init__.py
dodrio/afeat/__init__.py
dodrio/afeat/exp_audiof.py
dodrio/afeat/exp_fun.py
dodrio/afeat/exp_load.py
dodrio/afeat/feat_extractor.py
dodrio/core/__init__.py
dodrio/core/datainfo_process.py
dodrio/core/load_info.py
dodrio/core/package_base.py
dodrio/core/parquet_base.py
dodrio/core/utils.py
dodrio/genlist/__init__.py
dodrio/genlist/gendatalist.py
dodrio/tools/__init__.py
dodrio/tools/load_data.py
dodrio-0.3.8.dist-info/METADATA
dodrio-0.3.8.dist-info/WHEEL
dodrio-0.3.8.dist-info/top_level.txt
dodrio-0.3.8.dist-info/RECORD
